sudokumizer/__init__.py
sudokumizer/board.py
sudokumizer-0.0.6.dist-info/AUTHORS.rst
sudokumizer-0.0.6.dist-info/LICENSE
sudokumizer-0.0.6.dist-info/METADATA
sudokumizer-0.0.6.dist-info/WHEEL
sudokumizer-0.0.6.dist-info/top_level.txt
sudokumizer-0.0.6.dist-info/RECORD
