Metadata-Version: 2.1
Name: sudokumizer
Version: 0.0.6
Summary: Returns a Sudoku board sollution as a numpy 2d array. Use as a starting point for your own Sudoku creations.
Home-page: https://github.com/tomasforsman/sudokumizer
Author: Tomas Forsman
Author-email: tomas@forsman.dev
License: MIT
Keywords: sudokumizer
Platform: UNKNOWN
Classifier: Development Status :: 2 - Pre-Alpha
Classifier: Intended Audience :: Developers
Classifier: License :: OSI Approved :: MIT License
Classifier: Natural Language :: English
Classifier: Programming Language :: Python :: 3.7
Classifier: Programming Language :: Python :: Implementation :: PyPy
